{
  "yaakVersion": "2026.3.1",
  "yaakSchema": 4,
  "timestamp": "2026-07-04T04:56:29.748485375",
  "resources": {
    "workspaces": [
      {
        "model": "workspace",
        "id": "wk_5fHFYX4Z4G",
        "createdAt": "2026-07-04T03:55:45.994575237",
        "updatedAt": "2026-07-04T03:55:45.994576630",
        "authentication": {},
        "authenticationType": null,
        "description": "",
        "headers": [],
        "name": "MoonCart",
        "encryptionKeyChallenge": null,
        "settingValidateCertificates": true,
        "settingFollowRedirects": true,
        "settingRequestTimeout": 0,
        "settingDnsOverrides": []
      }
    ],
    "environments": [],
    "folders": [
      {
        "model": "folder",
        "id": "fl_ZZDFH2UHXJ",
        "createdAt": "2026-07-04T04:05:10.099295405",
        "updatedAt": "2026-07-04T04:05:24.080438088",
        "workspaceId": "wk_5fHFYX4Z4G",
        "folderId": null,
        "authentication": {},
        "authenticationType": null,
        "description": "",
        "headers": [],
        "name": "Reconcillation",
        "sortPriority": -1783137910098.0
      },
      {
        "model": "folder",
        "id": "fl_yyeMxabfos",
        "createdAt": "2026-07-04T04:04:26.648002824",
        "updatedAt": "2026-07-04T04:04:26.648004489",
        "workspaceId": "wk_5fHFYX4Z4G",
        "folderId": null,
        "authentication": {},
        "authenticationType": null,
        "description": "",
        "headers": [],
        "name": "Investigate",
        "sortPriority": -1783137866646.0
      },
      {
        "model": "folder",
        "id": "fl_JbqLhumYvH",
        "createdAt": "2026-07-04T04:04:06.147328806",
        "updatedAt": "2026-07-04T04:04:06.147330299",
        "workspaceId": "wk_5fHFYX4Z4G",
        "folderId": null,
        "authentication": {},
        "authenticationType": null,
        "description": "",
        "headers": [],
        "name": "Ingestion",
        "sortPriority": -1783137846146.0
      }
    ],
    "httpRequests": [
      {
        "model": "http_request",
        "id": "rq_XidCsN8QJg",
        "createdAt": "2026-07-04T04:49:29.384571558",
        "updatedAt": "2026-07-04T04:50:11.383999887",
        "workspaceId": "wk_5fHFYX4Z4G",
        "folderId": "fl_yyeMxabfos",
        "authentication": {},
        "authenticationType": null,
        "body": {},
        "bodyType": null,
        "description": "",
        "headers": [],
        "method": "GET",
        "name": "Statistics trends",
        "sortPriority": 0.001,
        "url": "http://localhost:8080/api/v1/statistics/trends",
        "urlParameters": [
          {
            "enabled": true,
            "name": "runId",
            "value": "96d030b2-c66f-46ad-b1cc-26760770b3c7",
            "id": "G3GxPAIETY"
          },
          {
            "enabled": true,
            "name": "type",
            "value": "UNMATCHED_SETTLEMENT",
            "id": "HYe3uQIiw7"
          },
          {
            "enabled": true,
            "name": "page",
            "value": "0",
            "id": "QKvkNeS4D4"
          },
          {
            "enabled": true,
            "name": "size",
            "value": "10",
            "id": "Iw0xke4kUu"
          },
          {
            "enabled": true,
            "name": "",
            "value": "",
            "id": "R5gyzukAW5"
          }
        ]
      },
      {
        "model": "http_request",
        "id": "rq_shLUoB9YzT",
        "createdAt": "2026-07-04T04:19:58.456785995",
        "updatedAt": "2026-07-04T04:20:14.780833668",
        "workspaceId": "wk_5fHFYX4Z4G",
        "folderId": "fl_yyeMxabfos",
        "authentication": {},
        "authenticationType": null,
        "body": {},
        "bodyType": null,
        "description": "",
        "headers": [],
        "method": "GET",
        "name": "Statistics summary",
        "sortPriority": 0.002,
        "url": "http://localhost:8080/api/v1/statistics/summary",
        "urlParameters": [
          {
            "enabled": true,
            "name": "runId",
            "value": "96d030b2-c66f-46ad-b1cc-26760770b3c7",
            "id": "Mg3VEgyTKd"
          },
          {
            "enabled": true,
            "name": "",
            "value": "",
            "id": "FCXSZBxRaF"
          }
        ]
      },
      {
        "model": "http_request",
        "id": "rq_cjpkoebHA6",
        "createdAt": "2026-07-04T04:19:25.325008157",
        "updatedAt": "2026-07-04T04:19:43.116302308",
        "workspaceId": "wk_5fHFYX4Z4G",
        "folderId": "fl_yyeMxabfos",
        "authentication": {},
        "authenticationType": null,
        "body": {},
        "bodyType": null,
        "description": "",
        "headers": [],
        "method": "GET",
        "name": "Investigation Queue",
        "sortPriority": 0.001,
        "url": "http://localhost:8080/api/v1/investigation-queue",
        "urlParameters": [
          {
            "enabled": true,
            "name": "runId",
            "value": "96d030b2-c66f-46ad-b1cc-26760770b3c7",
            "id": "37wrVv56Z3"
          },
          {
            "enabled": true,
            "name": "limit",
            "value": "20",
            "id": "3HvHcJDKcM"
          },
          {
            "enabled": true,
            "name": "",
            "value": "",
            "id": "I9qV9G5YD7"
          }
        ]
      },
      {
        "model": "http_request",
        "id": "rq_PNq28ZL3Wr",
        "createdAt": "2026-07-04T04:17:47.089152097",
        "updatedAt": "2026-07-04T04:18:45.385353279",
        "workspaceId": "wk_5fHFYX4Z4G",
        "folderId": "fl_yyeMxabfos",
        "authentication": {},
        "authenticationType": null,
        "body": {},
        "bodyType": null,
        "description": "",
        "headers": [],
        "method": "GET",
        "name": "Discrepancies",
        "sortPriority": 0.0,
        "url": "http://localhost:8080/api/v1/discrepancies",
        "urlParameters": [
          {
            "enabled": true,
            "name": "runId",
            "value": "96d030b2-c66f-46ad-b1cc-26760770b3c7",
            "id": "G3GxPAIETY"
          },
          {
            "enabled": true,
            "name": "type",
            "value": "UNMATCHED_SETTLEMENT",
            "id": "HYe3uQIiw7"
          },
          {
            "enabled": true,
            "name": "page",
            "value": "0",
            "id": "QKvkNeS4D4"
          },
          {
            "enabled": true,
            "name": "size",
            "value": "10",
            "id": "Iw0xke4kUu"
          },
          {
            "enabled": true,
            "name": "",
            "value": "",
            "id": "R5gyzukAW5"
          }
        ]
      },
      {
        "model": "http_request",
        "id": "rq_M7SAhT5esV",
        "createdAt": "2026-07-04T04:11:43.339587815",
        "updatedAt": "2026-07-04T04:12:02.133797881",
        "workspaceId": "wk_5fHFYX4Z4G",
        "folderId": "fl_ZZDFH2UHXJ",
        "authentication": {},
        "authenticationType": null,
        "body": {},
        "bodyType": null,
        "description": "",
        "headers": [],
        "method": "GET",
        "name": "Get Report",
        "sortPriority": 0.001,
        "url": "http://localhost:8080/api/v1/reconciliation/runs/:RUN_ID/report",
        "urlParameters": [
          {
            "enabled": true,
            "name": ":RUN_ID",
            "value": "96d030b2-c66f-46ad-b1cc-26760770b3c7",
            "id": "pPQ9DwGMXx"
          },
          {
            "enabled": true,
            "name": "",
            "value": "",
            "id": "RIwMGhmBYu"
          }
        ]
      },
      {
        "model": "http_request",
        "id": "rq_RW75HSX294",
        "createdAt": "2026-07-04T04:05:29.267710771",
        "updatedAt": "2026-07-04T04:06:34.953633702",
        "workspaceId": "wk_5fHFYX4Z4G",
        "folderId": "fl_ZZDFH2UHXJ",
        "authentication": {},
        "authenticationType": null,
        "body": {},
        "bodyType": null,
        "description": "",
        "headers": [],
        "method": "POST",
        "name": "Execute matching",
        "sortPriority": 0.0,
        "url": "http://localhost:8080/api/v1/reconciliation/runs/:RUN_ID/execute",
        "urlParameters": [
          {
            "enabled": true,
            "name": ":RUN_ID",
            "value": "96d030b2-c66f-46ad-b1cc-26760770b3c7",
            "id": "pPQ9DwGMXx"
          },
          {
            "enabled": true,
            "name": "",
            "value": "",
            "id": "RIwMGhmBYu"
          }
        ]
      },
      {
        "model": "http_request",
        "id": "rq_79HAevrJKe",
        "createdAt": "2026-07-04T04:01:27.227752711",
        "updatedAt": "2026-07-04T04:04:11.463803155",
        "workspaceId": "wk_5fHFYX4Z4G",
        "folderId": "fl_JbqLhumYvH",
        "authentication": {},
        "authenticationType": null,
        "body": {
          "form": [
            {
              "enabled": true,
              "file": "/home/binz/IdeaProjects/mooncartsettlement/build/testdata/internal_orders.csv",
              "id": "CptFckXZv3",
              "name": "file"
            },
            {
              "enabled": true,
              "id": "2ua34Ct6Dn",
              "name": "",
              "value": ""
            }
          ]
        },
        "bodyType": "multipart/form-data",
        "description": "",
        "headers": [
          {
            "enabled": true,
            "name": "Content-Type",
            "value": "multipart/form-data",
            "id": null
          }
        ],
        "method": "POST",
        "name": "Ingest orders",
        "sortPriority": 3000.0,
        "url": "http://localhost:8080/api/v1/ingest/orders",
        "urlParameters": [
          {
            "enabled": true,
            "name": "runId",
            "value": "96d030b2-c66f-46ad-b1cc-26760770b3c7",
            "id": "gbYKazZxNz"
          },
          {
            "enabled": true,
            "name": "",
            "value": "",
            "id": "J9JbS2GMCy"
          }
        ]
      },
      {
        "model": "http_request",
        "id": "rq_NLkTeApcDN",
        "createdAt": "2026-07-04T04:01:24.589030097",
        "updatedAt": "2026-07-04T04:04:11.441977425",
        "workspaceId": "wk_5fHFYX4Z4G",
        "folderId": "fl_JbqLhumYvH",
        "authentication": {},
        "authenticationType": null,
        "body": {
          "form": [
            {
              "enabled": true,
              "file": "/home/binz/IdeaProjects/mooncartsettlement/build/testdata/bank_settlements.csv",
              "id": "CptFckXZv3",
              "name": "file"
            },
            {
              "enabled": true,
              "id": "jTqXvfF2b4",
              "name": "",
              "value": ""
            }
          ]
        },
        "bodyType": "multipart/form-data",
        "description": "",
        "headers": [
          {
            "enabled": true,
            "name": "Content-Type",
            "value": "multipart/form-data",
            "id": null
          }
        ],
        "method": "POST",
        "name": "Ingest bank",
        "sortPriority": 2000.0,
        "url": "http://localhost:8080/api/v1/ingest/bank-settlements",
        "urlParameters": [
          {
            "enabled": true,
            "name": "runId",
            "value": "96d030b2-c66f-46ad-b1cc-26760770b3c7",
            "id": "gbYKazZxNz"
          },
          {
            "enabled": true,
            "name": "",
            "value": "",
            "id": "J9JbS2GMCy"
          }
        ]
      },
      {
        "model": "http_request",
        "id": "rq_9ymLU5eKD6",
        "createdAt": "2026-07-04T04:00:20.981867274",
        "updatedAt": "2026-07-04T04:04:11.421056986",
        "workspaceId": "wk_5fHFYX4Z4G",
        "folderId": "fl_JbqLhumYvH",
        "authentication": {},
        "authenticationType": null,
        "body": {
          "form": [
            {
              "enabled": true,
              "file": "/home/binz/IdeaProjects/mooncartsettlement/build/testdata/yuno_transactions.csv",
              "id": "CptFckXZv3",
              "name": "file"
            },
            {
              "enabled": true,
              "id": "hBvx5hWRM7",
              "name": "",
              "value": ""
            }
          ]
        },
        "bodyType": "multipart/form-data",
        "description": "",
        "headers": [
          {
            "enabled": true,
            "name": "Content-Type",
            "value": "multipart/form-data",
            "id": null
          }
        ],
        "method": "POST",
        "name": "Ingest yuno",
        "sortPriority": 1000.0,
        "url": "http://localhost:8080/api/v1/ingest/yuno",
        "urlParameters": [
          {
            "enabled": true,
            "name": "runId",
            "value": "96d030b2-c66f-46ad-b1cc-26760770b3c7",
            "id": "gbYKazZxNz"
          },
          {
            "enabled": true,
            "name": "",
            "value": "",
            "id": "J9JbS2GMCy"
          }
        ]
      },
      {
        "model": "http_request",
        "id": "rq_oPwsz9pmed",
        "createdAt": "2026-07-04T03:59:55.490462550",
        "updatedAt": "2026-07-04T04:04:11.392000082",
        "workspaceId": "wk_5fHFYX4Z4G",
        "folderId": "fl_JbqLhumYvH",
        "authentication": {},
        "authenticationType": null,
        "body": {
          "text": "{\n  \"periodStart\": \"2026-03-01\",\n  \"periodEnd\": \"2026-03-30\"\n}"
        },
        "bodyType": "application/json",
        "description": "",
        "headers": [
          {
            "enabled": true,
            "name": "Content-Type",
            "value": "application/json",
            "id": null
          }
        ],
        "method": "POST",
        "name": "Create Run",
        "sortPriority": 0.0,
        "url": "http://localhost:8080/api/v1/reconciliation/runs",
        "urlParameters": []
      },
      {
        "model": "http_request",
        "id": "rq_HVbYZYYUVR",
        "createdAt": "2026-07-04T03:56:03.039203652",
        "updatedAt": "2026-07-04T03:56:18.300276565",
        "workspaceId": "wk_5fHFYX4Z4G",
        "folderId": null,
        "authentication": {},
        "authenticationType": null,
        "body": {},
        "bodyType": null,
        "description": "",
        "headers": [],
        "method": "GET",
        "name": "Home",
        "sortPriority": -1783137363038.0,
        "url": "localhost:8080/home",
        "urlParameters": []
      }
    ],
    "grpcRequests": [],
    "websocketRequests": []
  }
}